[
  {
    "name":"McDonald's",
    "url":"partnerLogo/mcdonalds.svg"
  },
  {
    "name":"Uber",
    "url":"partnerLogo/uber.svg"
  },
  {
    "name":"Ufo",
    "url":"partnerLogo/ufo.svg"
  },
  {
    "name":"Lon",
    "url":"partnerLogo/lon.svg"
  },
  {
    "name":"Kairos",
    "url":"partnerLogo/kairos.svg"
  },
  {
    "name":"Claustrophobia",
    "url":"partnerLogo/claustrophobia.svg"
  },
  {
    "name":"Lonmedia",
    "url":"partnerLogo/lonmedia.svg"
  },
  {
    "name":"Tarzania",
    "url":"partnerLogo/tarzania.svg"
  }
]